ecoengine/__init__.py
ecoengine/constants/Constants.py
ecoengine/constants/__init__.py
ecoengine/data/__init__.py
ecoengine/data/climate_data/DryBulbTemperatures_ByClimateZone.csv
ecoengine/data/climate_data/InletWaterTemperatures_ByClimateZone.csv
ecoengine/data/climate_data/WeatherStation_ClimateZone_Lookup.csv
ecoengine/data/climate_data/ZipCode_ClimateZone_Lookup.csv
ecoengine/data/climate_data/__init__.py
ecoengine/data/climate_data/kGperkWh_ByClimateZone.csv
ecoengine/data/load_shapes/__init__.py
ecoengine/data/load_shapes/apartment.json
ecoengine/data/load_shapes/elementary_school.json
ecoengine/data/load_shapes/food_service_a.json
ecoengine/data/load_shapes/food_service_b.json
ecoengine/data/load_shapes/junior_high.json
ecoengine/data/load_shapes/mens_dorm.json
ecoengine/data/load_shapes/motel.json
ecoengine/data/load_shapes/multi_family.json
ecoengine/data/load_shapes/nursing_home.json
ecoengine/data/load_shapes/office_building.json
ecoengine/data/load_shapes/senior_high.json
ecoengine/data/load_shapes/womens_dorm.json
ecoengine/data/preformanceMaps/__init__.py
ecoengine/data/preformanceMaps/maps.json
ecoengine/data/preformanceMaps/pkls/COLMAC_R454B_Single_Pass_bounds.pkl
ecoengine/data/preformanceMaps/pkls/COLMAC_R454B_Single_Pass_capacity_interpolator.pkl
ecoengine/data/preformanceMaps/pkls/COLMAC_R454B_Single_Pass_power_in_interpolator.pkl
ecoengine/data/preformanceMaps/pkls/Colmac_CxA10_Multi_Pass_bounds.pkl
ecoengine/data/preformanceMaps/pkls/Colmac_CxA10_Multi_Pass_capacity_interpolator.pkl
ecoengine/data/preformanceMaps/pkls/Colmac_CxA10_Multi_Pass_power_in_interpolator.pkl
ecoengine/data/preformanceMaps/pkls/Colmac_CxA10_Oversized_Condenser_Multi_Pass_bounds.pkl
ecoengine/data/preformanceMaps/pkls/Colmac_CxA10_Oversized_Condenser_Multi_Pass_capacity_interpolator.pkl
ecoengine/data/preformanceMaps/pkls/Colmac_CxA10_Oversized_Condenser_Multi_Pass_power_in_interpolator.pkl
ecoengine-2.0.2.dist-info/METADATA
ecoengine-2.0.2.dist-info/WHEEL
ecoengine-2.0.2.dist-info/top_level.txt
ecoengine-2.0.2.dist-info/RECORD
