Metadata-Version: 2.4
Name: ecoengine
Version: 2.0.2
Summary: A software for sizing Heat Pump Water Heaters for buildings
Home-page: https://ecosizer.ecotope.com/sizer/
Author: Nolan
Author-email: nolan@ecotope.com
Project-URL: Docs, https://ecosizer.ecotope.com/sizer/docs/
Classifier: Programming Language :: Python :: 3
Classifier: License :: OSI Approved :: GNU General Public License (GPL)
Classifier: Operating System :: OS Independent
Requires-Python: >=3.11
Requires-Dist: scipy
Requires-Dist: numpy
Requires-Dist: plotly
Requires-Dist: pytest
